tabs_data_preprocess/__init__.py
tabs_data_preprocess/book.py
tabs_data_preprocess/main.py
tabs_data_preprocess/trades.py
tabs_data_preprocess-0.1.1.dist-info/entry_points.txt
tabs_data_preprocess-0.1.1.dist-info/WHEEL
tabs_data_preprocess-0.1.1.dist-info/METADATA
tabs_data_preprocess-0.1.1.dist-info/RECORD
