Metadata-Version: 2.1
Name: tabs-data-preprocess
Version: 0.1.1
License: MIT
Author-email: Alexis Rosuel <rosuelalexis1@gmail.com>
Requires-Python: >=3.11
Requires-Dist: tabs-data-download>=0.1.4
